[{"dCount": "13/05/2011", "HGV": "27", "CAR": "654", "RCat": "PU", "Year": "2011", "PC": "2", "MV": "6", "BUS": "14", "lat": "51.614437690000003", "lng": "-0.326029034", "borough": "Harrow", "LGV": "88", "iDir": "E", "Road": "A410"}, {"dCount": "08/06/2011", "HGV": "13", "CAR": "473", "RCat": "PU", "Year": "2011", "PC": "0", "MV": "2", "BUS": "1", "lat": "51.615384980000002", "lng": "-0.360659854", "borough": "Harrow", "LGV": "51", "iDir": "N", "Road": "A4008"}, {"dCount": "18/03/2011", "HGV": "15", "CAR": "429", "RCat": "PU", "Year": "2011", "PC": "0", "MV": "1", "BUS": "10", "lat": "51.570215320000003", "lng": "-0.34641250400000001", "borough": "Harrow", "LGV": "45", "iDir": "N", "Road": "A312"}, {"dCount": "28/09/2011", "HGV": "35", "CAR": "606", "RCat": "PU", "Year": "2011", "PC": "9", "MV": "12", "BUS": "35", "lat": "51.60513031", "lng": "-0.27322903999999998", "borough": "Harrow", "LGV": "81", "iDir": "N", "Road": "A5"}, {"dCount": "23/05/2011", "HGV": "22", "CAR": "968", "RCat": "PU", "Year": "2011", "PC": "3", "MV": "6", "BUS": "20", "lat": "51.581678600000004", "lng": "-0.330408427", "borough": "Harrow", "LGV": "92", "iDir": "N", "Road": "A409"}]