[{"dCount": "2010-05-27", "HGV": "10", "CAR": "282", "RCat": "BU", "Year": "2010", "PC": "2", "MV": "2", "BUS": "20", "lat": "51.608695878999995", "lng": "-0.28581716899999998", "borough": "Harrow", "LGV": "34", "iDir": "N", "Road": "B461"}, {"dCount": "2010-06-24", "HGV": "7", "CAR": "357", "RCat": "CU", "Year": "2010", "PC": "2", "MV": "2", "BUS": "9", "lat": "51.587631575000003", "lng": "-0.34310974500000002", "borough": "Harrow", "LGV": "42", "iDir": "N", "Road": "C"}, {"dCount": "2010-10-18", "HGV": "0", "CAR": "6", "RCat": "UU", "Year": "2010", "PC": "0", "MV": "0", "BUS": "0", "lat": "51.580680808000004", "lng": "-0.35783885999999998", "borough": "Harrow", "LGV": "1", "iDir": "E", "Road": "U"}, {"dCount": "2010-04-28", "HGV": "2", "CAR": "91", "RCat": "UU", "Year": "2010", "PC": "2", "MV": "0", "BUS": "0", "lat": "51.605354626", "lng": "-0.395505736", "borough": "Harrow", "LGV": "11", "iDir": "E", "Road": "U"}, {"dCount": "2010-05-28", "HGV": "17", "CAR": "529", "RCat": "CU", "Year": "2010", "PC": "4", "MV": "4", "BUS": "14", "lat": "51.589637947", "lng": "-0.35662088299999994", "borough": "Harrow", "LGV": "68", "iDir": "N", "Road": "C"}, {"dCount": "2010-07-01", "HGV": "0", "CAR": "21", "RCat": "UU", "Year": "2010", "PC": "1", "MV": "0", "BUS": "0", "lat": "51.572823661999998", "lng": "-0.38063357399999997", "borough": "Harrow", "LGV": "1", "iDir": "N", "Road": "U"}]