[{"dCount": "21/04/2015", "HGV": "93", "CAR": "2621", "RCat": "PU", "Year": "2015", "PC": "3", "MV": "91", "BUS": "10", "lat": "51.396703860000002", "lng": "-0.24770980000000001", "borough": "Kingston upon Thames", "LGV": "612", "iDir": "E", "Road": "A3"}, {"dCount": "16/10/2015", "HGV": "134", "CAR": "2741", "RCat": "PU", "Year": "2015", "PC": "0", "MV": "47", "BUS": "11", "lat": "51.373397789999999", "lng": "-0.291731984", "borough": "Kingston upon Thames", "LGV": "582", "iDir": "E", "Road": "A3"}, {"dCount": "21/05/2015", "HGV": "6", "CAR": "366", "RCat": "PU", "Year": "2015", "PC": "12", "MV": "8", "BUS": "16", "lat": "51.389244899999994", "lng": "-0.30551462600000001", "borough": "Kingston upon Thames", "LGV": "55", "iDir": "E", "Road": "A243"}, {"dCount": "28/04/2015", "HGV": "45", "CAR": "1373", "RCat": "PU", "Year": "2015", "PC": "0", "MV": "67", "BUS": "10", "lat": "51.43403481", "lng": "-0.25695683600000002", "borough": "Kingston upon Thames", "LGV": "355", "iDir": "N", "Road": "A3"}, {"dCount": "20/04/2015", "HGV": "12", "CAR": "510", "RCat": "PU", "Year": "2015", "PC": "17", "MV": "15", "BUS": "11", "lat": "51.382378330000002", "lng": "-0.24828572300000001", "borough": "Kingston upon Thames", "LGV": "107", "iDir": "N", "Road": "A2043"}, {"dCount": "01/06/2015", "HGV": "104", "CAR": "2702", "RCat": "PU", "Year": "2015", "PC": "2", "MV": "69", "BUS": "22", "lat": "51.391849299999997", "lng": "-0.26229765700000002", "borough": "Kingston upon Thames", "LGV": "640", "iDir": "E", "Road": "A3"}, {"dCount": "23/04/2015", "HGV": "36", "CAR": "1621", "RCat": "PU", "Year": "2015", "PC": "69", "MV": "59", "BUS": "46", "lat": "51.412916180000003", "lng": "-0.30075695099999999", "borough": "Kingston upon Thames", "LGV": "286", "iDir": "S", "Road": "A308"}, {"dCount": "14/04/2015", "HGV": "112", "CAR": "2301", "RCat": "PR", "Year": "2015", "PC": "0", "MV": "54", "BUS": "4", "lat": "51.375538640000002", "lng": "-0.30602074400000001", "borough": "Kingston upon Thames", "LGV": "516", "iDir": "E", "Road": "A3"}, {"dCount": "01/07/2015", "HGV": "49", "CAR": "1185", "RCat": "PU", "Year": "2015", "PC": "12", "MV": "28", "BUS": "20", "lat": "51.375883819999999", "lng": "-0.27727086699999998", "borough": "Kingston upon Thames", "LGV": "239", "iDir": "N", "Road": "A240"}, {"dCount": "11/06/2015", "HGV": "5", "CAR": "175", "RCat": "PU", "Year": "2015", "PC": "1", "MV": "2", "BUS": "1", "lat": "51.416423729999998", "lng": "-0.25187425699999999", "borough": "Kingston upon Thames", "LGV": "29", "iDir": "E", "Road": "A238"}, {"dCount": "09/06/2015", "HGV": "1", "CAR": "97", "RCat": "PU", "Year": "2015", "PC": "1", "MV": "1", "BUS": "0", "lat": "51.41516764", "lng": "-0.25206598199999997", "borough": "Kingston upon Thames", "LGV": "19", "iDir": "N", "Road": "A3"}, {"dCount": "13/04/2015", "HGV": "1", "CAR": "45", "RCat": "PU", "Year": "2015", "PC": "4", "MV": "1", "BUS": "0", "lat": "51.415584840000001", "lng": "-0.24989290600000003", "borough": "Kingston upon Thames", "LGV": "15", "iDir": "S", "Road": "A3"}, {"dCount": "02/06/2015", "HGV": "1", "CAR": "133", "RCat": "PU", "Year": "2015", "PC": "1", "MV": "2", "BUS": "0", "lat": "51.382486960000001", "lng": "-0.27989707699999999", "borough": "Kingston upon Thames", "LGV": "20", "iDir": "E", "Road": "A240"}, {"dCount": "09/10/2015", "HGV": "97", "CAR": "2485", "RCat": "PU", "Year": "2015", "PC": "0", "MV": "58", "BUS": "11", "lat": "51.382269219999998", "lng": "-0.27731853400000001", "borough": "Kingston upon Thames", "LGV": "518", "iDir": "N", "Road": "A3"}]