[{"dCount": "11/06/2013", "HGV": "7", "CAR": "270", "RCat": "PU", "Year": "2013", "PC": "1", "MV": "4", "BUS": "20", "lat": "51.411697050000001", "lng": "0.014552549", "borough": "Bromley", "LGV": "39", "iDir": "N", "Road": "A2212"}, {"dCount": "10/09/2013", "HGV": "10", "CAR": "531", "RCat": "PU", "Year": "2013", "PC": "5", "MV": "14", "BUS": "9", "lat": "51.403888019999997", "lng": "-0.055523142999999997", "borough": "Bromley", "LGV": "102", "iDir": "N", "Road": "A214"}, {"dCount": "29/04/2013", "HGV": "17", "CAR": "688", "RCat": "PU", "Year": "2013", "PC": "1", "MV": "10", "BUS": "11", "lat": "51.415522969999998", "lng": "0.083752539000000001", "borough": "Bromley", "LGV": "141", "iDir": "E", "Road": "A222"}, {"dCount": "04/07/2013", "HGV": "16", "CAR": "883", "RCat": "PU", "Year": "2013", "PC": "3", "MV": "19", "BUS": "17", "lat": "51.398340849999997", "lng": "-0.046413982999999999", "borough": "Bromley", "LGV": "272", "iDir": "E", "Road": "A222"}, {"dCount": "16/05/2013", "HGV": "13", "CAR": "464", "RCat": "PU", "Year": "2013", "PC": "4", "MV": "6", "BUS": "41", "lat": "51.380633179999997", "lng": "0.10372356199999999", "borough": "Bromley", "LGV": "86", "iDir": "W", "Road": "A223"}, {"dCount": "16/04/2013", "HGV": "29", "CAR": "651", "RCat": "PR", "Year": "2013", "PC": "0", "MV": "3", "BUS": "2", "lat": "51.355770069999998", "lng": "0.12599595299999999", "borough": "Bromley", "LGV": "117", "iDir": "N", "Road": "A224"}]