[{"dCount": "2014-10-08", "HGV": "3", "CAR": "248", "RCat": "BR", "Year": "2014", "PC": "1", "MV": "1", "BUS": "0", "lat": "51.341722673999996", "lng": "-0.16832567800000001", "borough": "Sutton", "LGV": "48", "iDir": "E", "Road": "B278"}, {"dCount": "2014-10-01", "HGV": "8", "CAR": "359", "RCat": "BU", "Year": "2014", "PC": "2", "MV": "5", "BUS": "4", "lat": "51.361012514999999", "lng": "-0.13078400800000001", "borough": "Sutton", "LGV": "76", "iDir": "N", "Road": "B272"}, {"dCount": "2014-07-04", "HGV": "6", "CAR": "519", "RCat": "BU", "Year": "2014", "PC": "7", "MV": "8", "BUS": "18", "lat": "51.352657828000005", "lng": "-0.19205998199999999", "borough": "Sutton", "LGV": "70", "iDir": "N", "Road": "B2230"}, {"dCount": "2014-06-13", "HGV": "24", "CAR": "336", "RCat": "CU", "Year": "2014", "PC": "5", "MV": "7", "BUS": "11", "lat": "51.385047101000005", "lng": "-0.17740382899999999", "borough": "Sutton", "LGV": "80", "iDir": "E", "Road": "C"}, {"dCount": "2014-05-01", "HGV": "1", "CAR": "175", "RCat": "CU", "Year": "2014", "PC": "3", "MV": "1", "BUS": "4", "lat": "51.358546850000003", "lng": "-0.19314954899999998", "borough": "Sutton", "LGV": "23", "iDir": "E", "Road": "C"}, {"dCount": "2014-05-20", "HGV": "0", "CAR": "32", "RCat": "UU", "Year": "2014", "PC": "0", "MV": "0", "BUS": "0", "lat": "51.365706916999997", "lng": "-0.20908643800000001", "borough": "Sutton", "LGV": "6", "iDir": "E", "Road": "U"}, {"dCount": "2014-05-01", "HGV": "0", "CAR": "57", "RCat": "UU", "Year": "2014", "PC": "0", "MV": "0", "BUS": "3", "lat": "51.356753691999998", "lng": "-0.18767608300000002", "borough": "Sutton", "LGV": "5", "iDir": "E", "Road": "U"}, {"dCount": "2014-09-15", "HGV": "0", "CAR": "3", "RCat": "UU", "Year": "2014", "PC": "0", "MV": "0", "BUS": "0", "lat": "51.349879379999997", "lng": "-0.18800477100000001", "borough": "Sutton", "LGV": "0", "iDir": "N", "Road": "U"}, {"dCount": "2014-05-23", "HGV": "0", "CAR": "4", "RCat": "UU", "Year": "2014", "PC": "0", "MV": "0", "BUS": "0", "lat": "51.351826771999995", "lng": "-0.16120168599999998", "borough": "Sutton", "LGV": "1", "iDir": "N", "Road": "U"}, {"dCount": "2014-09-29", "HGV": "0", "CAR": "54", "RCat": "UU", "Year": "2014", "PC": "0", "MV": "0", "BUS": "0", "lat": "51.353589278000001", "lng": "-0.15205445000000001", "borough": "Sutton", "LGV": "6", "iDir": "N", "Road": "U"}, {"dCount": "2014-05-08", "HGV": "28", "CAR": "570", "RCat": "BU", "Year": "2014", "PC": "2", "MV": "8", "BUS": "12", "lat": "51.370944227999999", "lng": "-0.13214673199999999", "borough": "Sutton", "LGV": "138", "iDir": "N", "Road": "B272"}, {"dCount": "2014-09-18", "HGV": "0", "CAR": "11", "RCat": "UU", "Year": "2014", "PC": "0", "MV": "0", "BUS": "0", "lat": "51.348150346000004", "lng": "-0.19834041300000002", "borough": "Sutton", "LGV": "1", "iDir": "N", "Road": "U"}, {"dCount": "2014-05-12", "HGV": "0", "CAR": "61", "RCat": "UU", "Year": "2014", "PC": "1", "MV": "0", "BUS": "0", "lat": "51.356550293000005", "lng": "-0.134053649", "borough": "Sutton", "LGV": "7", "iDir": "N", "Road": "U"}]