[{"dCount": "18/03/2016", "HGV": "3", "CAR": "212", "RCat": "PU", "Year": "2016", "PC": "4", "MV": "2", "BUS": "22", "lat": "51.551417469999997", "lng": "0.047260524999999998", "borough": "Newham", "LGV": "31", "iDir": "N", "Road": "A117"}, {"dCount": "18/05/2016", "HGV": "6", "CAR": "341", "RCat": "PU", "Year": "2016", "PC": "7", "MV": "6", "BUS": "28", "lat": "51.527878399999999", "lng": "0.056296275", "borough": "Newham", "LGV": "46", "iDir": "N", "Road": "A117"}, {"dCount": "14/06/2016", "HGV": "258", "CAR": "2549", "RCat": "PU", "Year": "2016", "PC": "0", "MV": "35", "BUS": "9", "lat": "51.551690049999998", "lng": "0.067611415999999994", "borough": "Newham", "LGV": "685", "iDir": "N", "Road": "A406"}, {"dCount": "21/09/2016", "HGV": "5", "CAR": "377", "RCat": "PU", "Year": "2016", "PC": "18", "MV": "9", "BUS": "28", "lat": "51.53179866", "lng": "0.016966961999999999", "borough": "Newham", "LGV": "71", "iDir": "E", "Road": "A112"}, {"dCount": "06/07/2016", "HGV": "229", "CAR": "2358", "RCat": "PU", "Year": "2016", "PC": "13", "MV": "134", "BUS": "25", "lat": "51.514817549999997", "lng": "0.0050756000000000004", "borough": "Newham", "LGV": "727", "iDir": "E", "Road": "A13"}]